rdtools/__init__.py
rdtools/_deprecation.py
rdtools/_version.py
rdtools/aggregation.py
rdtools/analysis_chains.py
rdtools/availability.py
rdtools/bootstrap.py
rdtools/clearsky_temperature.py
rdtools/degradation.py
rdtools/filtering.py
rdtools/normalization.py
rdtools/plotting.py
rdtools/soiling.py
rdtools/utilities.py
rdtools/data/temperature.hdf5
rdtools/models/xgboost_clipping_model.json
rdtools-3.0.1.dist-info/licenses/LICENSE
rdtools-3.0.1.dist-info/METADATA
rdtools-3.0.1.dist-info/WHEEL
rdtools-3.0.1.dist-info/top_level.txt
rdtools-3.0.1.dist-info/RECORD
